derivx/__init__.py
derivx/_version.py
derivx/curves.py
derivx/analytic/__init__.py
derivx/analytic/bs.py
derivx/analytic/haug.py
derivx/dsl/spec.py
derivx/engine/montecarlo.py
derivx/exercise/lsmc.py
derivx/ir/__init__.py
derivx/ir/black76.py
derivx/models/gbm.py
derivx/payoffs/core.py
derivx/payoffs/extra.py
derivx/report/__init__.py
derivx/report/plot.py
derivx/report/test_plot_report.py
derivx_precificador-0.1.1.dist-info/METADATA
derivx_precificador-0.1.1.dist-info/WHEEL
derivx_precificador-0.1.1.dist-info/top_level.txt
derivx_precificador-0.1.1.dist-info/RECORD
