Metadata-Version: 2.4
Name: derivx-precificador
Version: 0.1.1
Summary: Precificador de derivativos em Python (MC/LSMC, PDE CN, FFT Heston, IR Black-76) com DSL declarativa.
Author: Walter C. Neto
License: MIT
Project-URL: Homepage, https://github.com/walterCNeto/precificador
Project-URL: Repository, https://github.com/walterCNeto/precificador
Project-URL: Issues, https://github.com/walterCNeto/precificador/issues
Keywords: options,derivatives,pricing,Monte Carlo,LSMC,PDE,FFT,Heston,Black76,DSL
Requires-Python: >=3.11
Requires-Dist: numpy>=1.26
Requires-Dist: scipy>=1.11
Provides-Extra: dev
Requires-Dist: pytest>=7; extra == "dev"
Requires-Dist: pytest-cov>=4; extra == "dev"
Requires-Dist: matplotlib>=3.8; extra == "dev"
Requires-Dist: build>=1.2; extra == "dev"
Requires-Dist: twine>=5.0; extra == "dev"
